<?xml version="1.0"?>
<psalm
    runTaintAnalysis="true"
>
    <projectFiles>
        <directory name="front" />
        <directory name="src" />
        <file name="hook.php" />
        <file name="setup.php" />
    </projectFiles>

    <issueHandlers>
        <!--
            Too many false positives.
            - many are already secured by ForbidDynamicInstantiationRule, but Psalm does not seems to consider `is_a()` checks safe enough;
            - many are related dynamic call to plugin functions/classes, we need a lot of refactor to indicate to Psalm these can be ignored;
            - the rest is likely to not be exploitable, due to the really low probability to have a classname
              that can be abused and that implements the specific static method called on a dynamic classname.
        -->
        <TaintedCallable errorLevel="suppress" />
    </issueHandlers>
</psalm>
